examples/gnn_dispatch/Params.py
examples/gnn_dispatch/__init__.py
examples/gnn_dispatch/global_util.py
examples/gnn_dispatch/my_memory.py
examples/gnn_dispatch/runner.py
examples/gnn_dispatch/train_ppo.py
examples/gnn_dispatch/env/__init__.py
examples/gnn_dispatch/env/base_env.py
examples/gnn_dispatch/env/jssp_env.py
jssp_tool/__init__.py
jssp_tool/env/__init__.py
jssp_tool/env/base_env.py
jssp_tool/env/operation_machine_helper.py
jssp_tool/env/data/__init__.py
jssp_tool/env/data/data_generator.py
jssp_tool/env/util/__init__.py
jssp_tool/env/util/config_util.py
jssp_tool/env/util/random_util.py
jssp_tool/env/util/time_util.py
jssp_tool/env/util/torch_util.py
jssp_tool/plotter/__init__.py
jssp_tool/plotter/gantt_plot.py
jssp_tool/plotter/network_plot.py
jssp_tool/rl/__init__.py
jssp_tool/rl/agent/__init__.py
jssp_tool/rl/agent/dqn/__init__.py
jssp_tool/rl/agent/dqn/ddqn.py
jssp_tool/rl/agent/ppo/__init__.py
jssp_tool/rl/agent/ppo/memory.py
jssp_tool/rl/agent/ppo/ppo_base.py
jssp_tool/rl/agent/ppo/ppo_discrete.py
jssp_tool/rl/epsilon_strategy/__init__.py
jssp_tool/rl/epsilon_strategy/linear_decay.py
jssp_tool/rl/replay_buffer/__init__.py
jssp_tool/rl/replay_buffer/replay_buffer.py
jssp_tool/rl/replay_buffer/a/__init__.py
jssp_tool/rl/replay_buffer/a/prioritized.py
jssp_tool/rl/replay_buffer/a/random.py
jssp_tool/rl/replay_buffer/a/sum_tree.py
jssp_tool/rl/replay_buffer/priority/__init__.py
jssp_tool/rl/replay_buffer/priority/priority_replay_buffer.py
jssp_tool/rl/replay_buffer/priority/sum_tree.py
jssp_tool/util/__init__.py
jssp_tool/util/logger.py
jssp_tool-1.0.9.dist-info/METADATA
jssp_tool-1.0.9.dist-info/WHEEL
jssp_tool-1.0.9.dist-info/top_level.txt
jssp_tool-1.0.9.dist-info/RECORD
